HISTORY.rst
LICENSE
MANIFEST.in
README.rst
make.py
requirements.txt
setup.py
test-requirements.txt
bingads/__init__.py
bingads/authorization.py
bingads/exceptions.py
bingads/manifest.py
bingads/service_client.py
bingads/service_info.py
bingads/util.py
bingads/internal/__init__.py
bingads/internal/error_messages.py
bingads/v13/__init__.py
bingads/v13/bulk/__init__.py
bingads/v13/bulk/bulk_operation.py
bingads/v13/bulk/bulk_operation_progress_info.py
bingads/v13/bulk/bulk_operation_status.py
bingads/v13/bulk/bulk_service_manager.py
bingads/v13/bulk/download_parameters.py
bingads/v13/bulk/enums.py
bingads/v13/bulk/exceptions.py
bingads/v13/bulk/file_reader.py
bingads/v13/bulk/file_writer.py
bingads/v13/bulk/upload_parameters.py
bingads/v13/bulk/entities/__init__.py
bingads/v13/bulk/entities/bid_suggestion_data.py
bingads/v13/bulk/entities/bulk_account.py
bingads/v13/bulk/entities/bulk_account_negative_keyword_list.py
bingads/v13/bulk/entities/bulk_ad_customizer_attribute.py
bingads/v13/bulk/entities/bulk_ad_customizer_attribute_ad_group.py
bingads/v13/bulk/entities/bulk_ad_customizer_attribute_campaign.py
bingads/v13/bulk/entities/bulk_ad_customizer_attribute_entity_base.py
bingads/v13/bulk/entities/bulk_ad_customizer_attribute_keyword.py
bingads/v13/bulk/entities/bulk_ad_group.py
bingads/v13/bulk/entities/bulk_ad_group_criterion.py
bingads/v13/bulk/entities/bulk_ad_group_dynamic_search_ad_target.py
bingads/v13/bulk/entities/bulk_ad_group_hotel_listing_group.py
bingads/v13/bulk/entities/bulk_ad_group_negative_dynamic_search_ad_target.py
bingads/v13/bulk/entities/bulk_ad_group_product_partition.py
bingads/v13/bulk/entities/bulk_ads.py
bingads/v13/bulk/entities/bulk_asset_group.py
bingads/v13/bulk/entities/bulk_asset_group_listing_group.py
bingads/v13/bulk/entities/bulk_asset_group_search_theme.py
bingads/v13/bulk/entities/bulk_asset_group_url_target.py
bingads/v13/bulk/entities/bulk_audience_group.py
msads.egg-info/PKG-INFO
msads.egg-info/SOURCES.txt
msads.egg-info/dependency_links.txt
msads.egg-info/not-zip-safe
msads.egg-info/requires.txt
msads.egg-info/top_level.txt
