Metadata-Version: 1.1
Name: msads
Version: 13.0.25.2
Summary: A library to make working with the Bing Ads APIs and bulk services easy
Home-page: https://github.com/BingAds/BingAds-Python-SDK
Author: Bing Ads SDK Team
Author-email: bing_ads_sdk@microsoft.com
License: MIT
Keywords: bingads
Platform: UNKNOWN
Classifier: Development Status :: 5 - Production/Stable
Classifier: Intended Audience :: Developers
Classifier: License :: OSI Approved :: MIT License
Classifier: Natural Language :: English
Classifier: Operating System :: OS Independent
Classifier: Programming Language :: Python
Classifier: Programming Language :: Python :: 3
Classifier: Programming Language :: Python :: 3.8
Classifier: Programming Language :: Python :: 3.9
Classifier: Programming Language :: Python :: 3.10
Classifier: Programming Language :: Python :: 3.11
Classifier: Programming Language :: Python :: 3.12
